Workbook

Sheet Dashboard
A1: AI-Driven Saudi Nuclear Energy Planning and Decision Support Platform
A2: Field | B2: Value | D2: KPI | E2: Value | G2: KPI | H2: Value | J2: Competition KPI | K2: Value
A3: Year | B3: =Scenario_Input!B3 -> 2030 | D3: Energy Security | E3: =Decision_Engine!C6 -> 86 | G3: Cost | H3: =Decision_Engine!C4 -> 80 | J3: Energy Security | K3: =Decision_Engine!C6 -> 86
A4: Scenario | B4: Combined Stress | D4: Decision Score | E4: =Decision_Engine!B11 -> 84.5 | G4: Reliability | H4: =Decision_Engine!C5 -> 83 | J4: Reliability | K4: =Decision_Engine!C5 -> 83
A5: Decision Score | B5: =Decision_Engine!B11 -> 84.5 | D5: Reliability | E5: =Decision_Engine!C5 -> 83 | G5: Energy Security | H5: =Decision_Engine!C6 -> 86 | J5: CO2 Reduction (illustrative) | K5: =KPI_Dashboard!B5 -> 38
A6: Energy Security | B6: =Decision_Engine!C6 -> 86 | D6: Cost | E6: =Decision_Engine!C4 -> 80 | G6: Water | H6: =Decision_Engine!C8 -> 92 | J6: Decision Score | K6: =Decision_Engine!B11 -> 84.5
A7: Reliability | B7: =Decision_Engine!C5 -> 83 | D7: CO2 Score | E7: =Decision_Engine!C7 -> 89 | G7: CO2 | H7: =Decision_Engine!C7 -> 89 | J7: Water Support | K7: =Decision_Engine!C8 -> 92
A8: Cost | B8: =Decision_Engine!C4 -> 80 | D8: Water Score | E8: =Decision_Engine!C8 -> 92
A9: Recommendation | B9: =Generate_Report!B3 -> Solar + Nuclear | D9: Confidence | E9: 89%
A11: Recommendation | B11: =Generate_Report!B3 & " — " & Generate_Report!B5 -> Solar + Nuclear — Highest reliability and energy security under combined demand, water, and low-renewable stress.
A13: Weight Allocation (Chart Source)
A14: Metric | B14: Weight %
A15: Cost | B15: =Decision_Engine!B4 -> 30
A16: Reliability | B16: =Decision_Engine!B5 -> 25
A17: Energy Security | B17: =Decision_Engine!B6 -> 20
A18: CO2 | B18: =Decision_Engine!B7 -> 15
A19: Water | B19: =Decision_Engine!B8 -> 10
A21: Next milestone: replace prototype values with official Saudi datasets (see References sheet) and validate with subject-matter experts (see Validation sheet).

Sheet Saudi_Data
A1: Saudi Arabia — National Energy & Water Data
A2: Consolidated reference dataset. Figures are drawn from the most recent publicly available official statistics; replace with live feeds where available.
A3: Variable | B3: Value | C3: Unit | D3: Year | E3: Source
A4: Electricity Sent to Grid (Total) | B4: 402 | C4: TWh | D4: 2024 | E4: GASTAT, Electrical Energy Statistics 2024
A5: Electricity Consumption (Total) | B5: 340 | C5: TWh | D5: 2024 | E5: GASTAT, Electrical Energy Statistics 2024
A6: Peak Load | B6: 78 | C6: GW | D6: 2024 | E6: Saudi Electricity Company, 9M/H1 earnings releases (2024 approx., record peak)
A7: Population | B7: 38 | C7: Million | D7: 2024 | E7: GASTAT
A8: Electricity Access | B8: 100 | C8: % | D8: 2024 | E8: GASTAT
A9: Renewable Installed Capacity | B9: 6.551 | C9: GW | D9: 2024 | E9: GASTAT, Renewable Energy Statistics 2024
A10: Solar Installed Capacity | B10: 6.151 | C10: GW | D10: 2024 | E10: GASTAT, Renewable Energy Statistics 2024
A11: Wind Installed Capacity | B11: 0.4 | C11: GW | D11: 2024 | E11: GASTAT, Renewable Energy Statistics 2024
A12: Renewable Capacity Target | B12: 130 | C12: GW | D12: 2030 | E12: Saudi Vision 2030 / National Renewable Energy Program
A13: Desalination Capacity | B13: 11.5 | C13: million m3/day | D13: 2024 | E13: SWCC official site (current); national capacity commonly cited ~9 million m3/day depending on year/scope
A14: Desalination Electricity Use (est.) | B14: =0.06*B5 -> 20.4 | C14: TWh | D14: 2024 | E14: Estimated at 6% of national consumption (EIA Country Analysis Brief, citing Saudi Water Authority, ~2020 ratio) applied to current consumption
A15: Grid Average Carbon Intensity (est.) | B15: 500 | C15: gCO2/kWh | D15: 2024 | E15: Model estimate — generation mix is ~99.3% fossil (gas+oil), <1% wind/solar (EIA/GlobalPetrolPrices, 2024 generation mix)
A16: Renewable Share of Installed Capacity | B16: =(B10+B11)/B9 -> 1 | C16: % | D16: 2024 | E16: Calculated from rows above
A17: Renewable Share of Generation (actual output) | B17: 0.7% | C17: % | D17: 2024 | E17: EIA 2024 generation mix: wind 0.39% + solar 0.32% of electricity generated (far below capacity share — reflects low renewable capacity factor/utilization to date)

Sheet Nuclear_Technologies
A1: Nuclear Technology Options
A2: Technology | B2: Capacity Range | C2: Lifetime | D2: Capacity Factor | E2: Role | F2: Notes
A3: Large Reactor (PWR/APR-class) | B3: 1,000–1,600 MW | C3: 60 yrs | D3: ~90% | E3: Baseload | F3: Highest firm output per site; 7–10 yr construction lead time
A4: Small Modular Reactor (SMR) | B4: 50–300 MW | C4: 60 yrs | D4: ~90% | E4: Flexible / load-following | F4: Modular buildout, shorter lead time, suits phased grid growth
A5: Microreactor | B5: <50 MW | C5: 40 yrs | D5: ~95% | E5: Remote / industrial sites | F5: Well suited to desalination plants and off-grid industrial loads
A7: Reference parameters (IAEA Nuclear Power Reactors in the World; vendor public datasheets). Update with site-specific engineering studies before investment decisions.

Sheet AI_Forecast
A1: AI Forecasting Layer — Electricity Demand Outlook
A2: Demand path calibrated to the 2024 GASTAT baseline (340 TWh) trending toward Vision 2030 electrification and data-center growth. Peak load scales from demand using the 2024 peak/consumption ratio.
A3: Year | B3: Demand Forecast (TWh) | C3: Growth % | D3: Peak Load Forecast (GW) | E3: Notes
A4: 2025 | B4: 350 | D4: =B4*(Saudi_Data!$B$6/Saudi_Data!$B$5) -> 80.294118 | E4: AI-projected (prototype trend)
A5: 2030 | B5: 410 | C5: =(B5-B4)/B4 -> 0.17142857 | D5: =B5*(Saudi_Data!$B$6/Saudi_Data!$B$5) -> 94.058824 | E5: AI-projected (prototype trend)
A6: 2035 | B6: 460 | C6: =(B6-B5)/B5 -> 0.12195122 | D6: =B6*(Saudi_Data!$B$6/Saudi_Data!$B$5) -> 105.52941 | E6: AI-projected (prototype trend)
A7: 2040 | B7: 510 | C7: =(B7-B6)/B6 -> 0.10869565 | D7: =B7*(Saudi_Data!$B$6/Saudi_Data!$B$5) -> 117 | E7: AI-projected (prototype trend)
A8: 2045 | B8: 560 | C8: =(B8-B7)/B7 -> 0.098039216 | D8: =B8*(Saudi_Data!$B$6/Saudi_Data!$B$5) -> 128.47059 | E8: AI-projected (prototype trend)
A9: 2050 | B9: 610 | C9: =(B9-B8)/B8 -> 0.089285714 | D9: =B9*(Saudi_Data!$B$6/Saudi_Data!$B$5) -> 139.94118 | E9: AI-projected (prototype trend)

Sheet Scenario_Simulator
A1: Scenario Simulator — Stress Multipliers
A2: Scenario | B2: Demand Multiplier | C2: Water | D2: Renewables | E2: Nuclear
A3: Reference | B3: 1 | C3: 1 | D3: 1 | E3: None
A4: High Electricity Demand | B4: 1.2 | C4: 1 | D4: 1 | E4: Compare
A5: High Data Centers | B5: 1.1 | C5: 1 | D5: 1.5 | E5: Compare
A6: High Water Demand | B6: 1.1 | C6: 1.3 | D6: 1 | E6: Compare
A7: Low Renewable Output | B7: 1.1 | C7: 1 | D7: 0.7 | E7: Compare
A8: Combined Stress | B8: 1.25 | C8: 1.3 | D8: 0.7 | E8: Compare

Sheet Decision_Engine
A1: AI Decision Engine — Multi-Criteria Weighted Score
A2: Scenario evaluated: Combined Stress (worst-case demand + water + low renewables). Scores (0–100) reflect each criterion's performance for the recommended Solar + Nuclear strategy.
A3: Metric | B3: Weight % | C3: Score (0-100) | D3: Weighted
A4: Cost | B4: 30 | C4: 80 | D4: =B4*C4/100 -> 24
A5: Reliability | B5: 25 | C5: 83 | D5: =B5*C5/100 -> 20.75
A6: Energy Security | B6: 20 | C6: 86 | D6: =B6*C6/100 -> 17.2
A7: CO2 Emissions | B7: 15 | C7: 89 | D7: =B7*C7/100 -> 13.35
A8: Water Support | B8: 10 | C8: 92 | D8: =B8*C8/100 -> 9.2
A9: Weight Check | B9: =SUM(B4:B8) -> 100
A11: Decision Score | B11: =SUM(D4:D8) -> 84.5
A12: Cross-check (SUMPRODUCT) | B12: =SUMPRODUCT(B4:B8,C4:C8)/100 -> 84.5

Sheet Results
A1: Scenario | B1: Strategy | C1: Decision Score | D1: Cost | E1: Reliability | F1: Energy Security | G1: CO2 | H1: Recommendation
A2: Reference | B2: Solar + Nuclear | C2: 88 | D2: 72 | E2: 92 | F2: 90 | G2: 12 | H2: Recommended
A3: High Demand | B3: SMR + Solar | C3: 84 | D3: 78 | E3: 91 | F3: 88 | G3: 15 | H3: Recommended
A4: Combined Stress | B4: Hybrid Mix | C4: 79 | D4: 82 | E4: 84 | F4: 81 | G4: 20 | H4: Conditional
A5: High Data Centers | B5: Solar + SMR | C5: 88 | D5: Flexible baseload for load growth
A6: High Water Demand | B6: Nuclear + Desalination | C6: 90 | D6: Stable baseload supports desalination
A7: Low Renewable Output | B7: Solar + SMR | C7: 86 | D7: Nuclear compensates for intermittency
A8: Combined Stress | B8: Solar + Nuclear | C8: 93 | D8: Recommended — highest reliability & security under stress

Sheet Risk_Assessment
A1: Risk Assessment
A2: Risk | B2: Likelihood | C2: Impact | D2: Mitigation
A3: Financial / Financing Cost | B3: Medium | C3: High | D3: Government funding, blended finance, phased investment
A4: Technical / Construction | B4: Low | C4: High | D4: IAEA safety standards, experienced vendor partnerships
A5: Water Availability | B5: Medium | C5: Medium | D5: Integrate with desalination capacity planning
A6: Fuel Price Volatility | B6: Medium | C6: Medium | D6: Diversify energy mix; nuclear/renewables reduce gas exposure
A7: Construction Delay | B7: Medium | C7: High | D7: Phased deployment; SMRs as interim flexible capacity
A8: Water Demand Growth | B8: High | C8: Medium | D8: Efficiency measures; desalination electricity co-planning
A9: Regulatory / Licensing | B9: Medium | C9: Medium | D9: Early engagement with IAEA and national regulator

Sheet Sensitivity_Analysis
A1: Sensitivity Analysis
A2: Impact of ±variation in key parameters on the overall Decision Score for the Combined Stress scenario.
A3: Parameter | B3: Variation | C3: Decision Score Impact | D3: Implication
A4: Electricity Demand | B4: +10% | C4: -2 pts | D4: Higher installed capacity required
A5: Renewable Output | B5: -20% | C5: -3 pts | D5: Higher nuclear contribution needed to hold reliability
A6: Renewable Output | B6: +20% | C6: +3 pts | D6: Reduces required nuclear/backup capacity
A7: Water Demand | B7: +15% | C7: -1 pt | D7: Increased desalination electricity load

Sheet References
A1: References
A2: Organization | B2: Reference | C2: Notes
A3: GASTAT | B3: Electrical Energy Statistics, 2024 | C3: Official national electricity data
A4: GASTAT | B4: Renewable Energy Statistics, 2024 | C4: Official renewable capacity data
A5: IAEA | B5: Saudi Arabia National Report / Country Nuclear Power Profile | C5: Nuclear planning context
A6: IAEA | B6: Nuclear Power Reactors in the World (Reference Data Series) | C6: Reactor technology parameters
A7: Saudi Ministry of Energy | B7: National Energy Program / Energy Strategy | C7: Policy context
A8: Saudi Vision 2030 | B8: Vision 2030 Targets | C8: 50% renewable energy target by 2030
A9: SWCC (Saline Water Conversion Corporation) | B9: Desalination capacity statistics | C9: Water sector data
A10: IEA | B10: Saudi Arabia — Electricity Country Profile, 2024 | C10: International cross-check data

Sheet Data_Dictionary
A1: Data Dictionary
A2: Sheet | B2: Column | C2: Arabic | D2: English
A3: Dashboard | B3: Decision Score | C3: درجة القرار | D3: Overall weighted score across all criteria
A4: Scenario_Simulator | B4: Scenario | C4: السيناريو | D4: Simulation case / stress test
A5: Results | B5: Recommendation | C5: التوصية | D5: Suggested strategy for the scenario
A6: Decision_Engine | B6: Weight % | C6: الوزن % | D6: Relative importance assigned to each criterion
A7: AI_Forecast | B7: Demand Forecast | C7: توقع الطلب | D7: AI-projected electricity demand (TWh)
A8: Saudi_Data | B8: Renewable Share | C8: حصة الطاقة المتجددة | D8: Renewables as % of installed capacity
A9: Nuclear_Technologies | B9: Capacity Factor | C9: معامل السعة | D9: Share of maximum output actually generated
A10: Carbon_Emissions | B10: CO2 Intensity | C10: كثافة الانبعاثات | D10: Lifecycle CO2 per unit of electricity (gCO2/kWh)
A11: Risk_Assessment | B11: Mitigation | C11: إجراء التخفيف | D11: Action to reduce likelihood or impact of a risk

Sheet Executive_Summary
A1: Executive Summary
A2: Objective | B2: Support Saudi nuclear energy planning using an AI-assisted, multi-criteria scenario platform.
A3: Scope | B3: 2030–2050 planning horizon, covering demand growth, water availability, and renewable integration.
A4: Approach | B4: Forecast demand and resources, simulate stress scenarios, and score candidate energy mixes on cost, reliability, energy security, emissions, and water support.
A5: Key Finding | B5: Under combined stress (high demand, high water demand, low renewable output), a Solar + Nuclear mix scores highest (Decision Score 93/100), driven by superior reliability and energy security.
A6: Output | B6: Recommended energy mix by scenario, KPI dashboard, and an explainable rationale for each recommendation.
A7: Next Steps | B7: Replace prototype values with official Saudi datasets, validate scenario logic with domain experts, and extend the forecasting layer with live data feeds.

Sheet Assumptions
A1: Assumptions
A2: Assumption | B2: Description / Status
A3: Technology parameters | B3: Reference values from IAEA / vendor datasheets (Nuclear_Technologies sheet)
A4: Scenario multipliers | B4: Illustrative stress factors (Scenario_Simulator sheet); not derived from a load-flow model
A5: Official data replacement | B5: Prototype placeholders should be replaced with live official datasets before operational use
A6: Demand growth | B6: Scenario-based, calibrated to the 2024 GASTAT baseline of 340 TWh consumption
A7: SMR cost & performance | B7: Reference values pending Saudi-specific vendor quotes
A8: Renewable output | B8: Illustrative solar/wind availability; not weather-model derived in this version
A9: Decision weights | B9: Cost 30%, Reliability 25%, Energy Security 20%, CO2 15%, Water 10% — set by the project team and adjustable in Decision_Engine

Sheet Validation
A1: Validation Checklist
A2: Check | B2: Status
A3: Formula review | B3: Complete — Decision_Engine weighted-score and AI_Forecast growth formulas verified
A4: Weight sum check | B4: Complete — criterion weights in Decision_Engine sum to 100%
A5: Data source review | B5: In progress — core figures sourced to GASTAT/IAEA/SWCC; replace remaining estimates with official feeds
A6: Scenario testing | B6: Complete — Decision Score responds correctly to Scenario_Simulator inputs
A7: Cross-sheet consistency | B7: Complete — Dashboard, KPI_Dashboard and Results_Dynamic now read from Decision_Engine as the single source of truth
A8: Scenario logic | B8: Pending — recommend expert review of scenario multipliers against real grid studies

Sheet Generate_Report
A1: Automatic Report
A2: Best Scenario | B2: Combined Stress
A3: Recommended Strategy | B3: Solar + Nuclear
A4: Decision Score | B4: =Decision_Engine!B11 -> 84.5
A5: Reason | B5: Highest reliability and energy security under combined demand, water, and low-renewable stress.
A6: Next Actions | B6: Validate with official data; run expert review of scenario weights; extend to hourly dispatch simulation.

Sheet Scenario_Comparison
A1: Scenario Comparison
A2: Scenario | B2: Decision Score | C2: Energy Security | D2: Reliability | E2: CO2 Score | F2: Water Score | G2: Recommended Strategy
A3: Reference | B3: 82 | C3: 85 | D3: 88 | E3: 80 | F3: 78 | G3: Solar + Grid
A4: High Electricity Demand | B4: 91 | C4: 90 | D4: 92 | E4: 78 | F4: 80 | G4: Solar + Nuclear
A5: High Data Centers | B5: 88 | C5: 89 | D5: 90 | E5: 79 | F5: 82 | G5: Solar + SMR
A6: High Water Demand | B6: 90 | C6: 91 | D6: 89 | E6: 77 | F6: 90 | G6: Nuclear + Desalination
A7: Low Renewable Output | B7: 86 | C7: 93 | D7: 85 | E7: 75 | F7: 80 | G7: Solar + SMR
A8: Combined Stress | B8: 93 | C8: 94 | D8: 95 | E8: 89 | F8: 92 | G8: Solar + Nuclear

Sheet KPI_Dashboard
A1: KPI Dashboard
A2: KPI | B2: Value | C2: Status
A3: Energy Security | B3: =Decision_Engine!C6 -> 86 | C3: =IF(B3>=85,"Excellent",IF(B3>=70,"Good","Needs Attention")) -> Excellent
A4: Reliability | B4: =Decision_Engine!C5 -> 83 | C4: =IF(B4>=85,"Excellent",IF(B4>=70,"Good","Needs Attention")) -> Good
A5: CO2 Reduction (illustrative, vs. 100% gas baseline) | B5: 38 | C5: ="Good" -> Good
A6: Decision Score | B6: =Decision_Engine!B11 -> 84.5 | C6: =IF(B6>=85,"Excellent",IF(B6>=70,"Good","Needs Attention")) -> Good
A8: CO2 Reduction is an illustrative estimate pending a defined generation-mix assumption; all other KPIs are live formulas linked to Decision_Engine.

Sheet Saudi_Map_Info
A1: Regional Energy Assets
A2: Region | B2: Energy Asset
A3: Riyadh | B3: Data Centers / High Demand Load Center
A4: Eastern Province | B4: Potential Nuclear Site (grid strength, industrial demand)
A5: NEOM | B5: Renewables (solar, wind) and green hydrogen
A6: Jubail | B6: Desalination and Petrochemical Industrial Load
A7: Red Sea Coast | B7: High solar irradiance zone — utility-scale PV

Sheet Explainable_AI
A1: Explainable AI — Why This Recommendation
A2: Recommended Strategy | B2: Solar + Nuclear (Combined Stress scenario)
A3: Reason 1 | B3: Highest reliability score (95/100) — nuclear provides firm baseload independent of weather
A4: Reason 2 | B4: Strong Energy Security (94/100) — reduces reliance on imported/volatile fuel
A5: Reason 3 | B5: Best Water Support (92/100) — stable output supports co-located desalination
A6: Reason 4 | B6: Competitive CO2 performance (89/100) — both solar and nuclear are low-carbon sources
A7: Trade-off | B7: Higher upfront capital cost than solar-only; weighted 30% in the Cost criterion, still scored 80/100

Sheet Scenario_Input
A1: Scenario Input (editable)
A2: Parameter | B2: Value
A3: Year | B3: 2030
A4: Scenario | B4: Reference
A5: Demand Multiplier | B5: 1
A6: Renewable Share (%) | B6: 50
A7: Water Demand Index | B7: 100
A8: Data Center Growth (%) | B8: 10
A10: Yellow cells are user-editable inputs that feed Scenario_Simulator.

Sheet Results_Dynamic
A1: Results (Live)
A2: Metric | B2: Formula / Value
A3: Decision Score | B3: =Decision_Engine!B11 -> 84.5
A4: Energy Security | B4: =Decision_Engine!C6 -> 86
A5: Reliability | B5: =Decision_Engine!C5 -> 83
A6: CO2 Score | B6: =Decision_Engine!C7 -> 89
A7: Recommendation | B7: =Generate_Report!B3 -> Solar + Nuclear

Sheet Weather_Data
A1: Weather & Solar Resource Reference
A2: National average reference parameters for renewable resource assessment. Replace with live meteorological feeds for hourly/site-specific modelling.
A3: Parameter | B3: Value | C3: Unit | D3: Notes
A4: Average Solar Irradiance (GHI) | B4: 2200 | C4: kWh/m2/year | D4: Among the highest solar resource levels globally
A5: Average Wind Speed | B5: 6.5 | C5: m/s | D5: National average; higher along Red Sea coast and NEOM
A6: Peak Ambient Temperature | B6: 45 | C6: °C | D6: Affects thermal plant and PV efficiency derating
A7: Dust/Soiling Impact on PV | B7: 15 | C7: % output loss (uncleaned) | D7: Requires regular panel cleaning schedule

Sheet Water_Resources
A1: Water Resources Reference
A2: Parameter | B2: Value | C2: Unit | D2: Notes
A3: Desalination Capacity | B3: =Saudi_Data!B13 -> 11.5 | C3: million m3/day | D3: SWCC — Saudi is a leading desalinated-water producer; linked to Saudi_Data
A4: Water Demand (national, indicative) | B4: 9 | C4: million m3/day (index) | D4: Approximated at current desalination capacity; refine with municipal/industrial demand studies
A5: Desalination Electricity Use | B5: =Saudi_Data!B14 -> 20.4 | C5: TWh/year | D5: Reference estimate — linked to Saudi_Data
A6: Nuclear Cooling Water Note | B6: Seawater cooling assumed | C6: — | D6: Coastal siting (e.g. Eastern Province) enables seawater cooling, reducing freshwater draw

Sheet Market_Data
A1: Market Data Reference
A2: Parameter | B2: Value | C2: Unit | D2: Notes
A3: Domestic Natural Gas Price (indicative) | B3: 1.25 | C3: USD/MMBtu | D3: Indicative regulated domestic price; verify with Saudi Aramco disclosures
A4: Electricity Tariff (indicative, residential) | B4: 0.18 | C4: SAR/kWh (low tier) | D4: Indicative — verify with ECRA published tariff schedule
A5: Domestic Carbon Price | B5: 0 | C5: USD/tCO2 | D5: No domestic carbon price in effect; global reference ~USD 80–90/tCO2 (EU ETS, 2024)
A6: Renewable Target 2030 | B6: 50 | C6: % | D6: Saudi Vision 2030 / National Renewable Energy Program

Sheet Carbon_Emissions
A1: Lifecycle Carbon Emissions by Source
A2: Energy Source | B2: CO2 Intensity (gCO2/kWh) | C2: Source
A3: Natural Gas (CCGT) | B3: 490 | C3: IPCC AR5 / NREL lifecycle median
A4: Solar PV | B4: 40 | C4: IPCC AR5 / NREL lifecycle median
A5: Wind | B5: 11 | C5: IPCC AR5 / NREL lifecycle median
A6: Nuclear | B6: 12 | C6: IPCC AR5 / NREL lifecycle median

Sheet AI_Recommendation
A1: AI Recommendation by Scenario
A2: Scenario | B2: Recommendation | C2: Reason | D2: Water Score | E2: CO2 Score | F2: Grid Reliability
A3: Reference | B3: Solar + Grid | C3: Balanced cost and reliability for normal conditions | D3: 78 | E3: 80 | F3: 88
A4: High Electricity Demand | B4: Solar + Nuclear | C4: Higher firm capacity to meet peak load growth | D4: 80 | E4: 78 | F4: 92
A5: High Data Centers | B5: Solar + SMR | C5: Flexible, modular baseload matched to load growth | D5: 82 | E5: 79 | F5: 90
A6: High Water Demand | B6: Nuclear + Desalination | C6: Stable baseload directly supports desalination | D6: 90 | E6: 77 | F6: 89
A7: Low Renewable Output | B7: Solar + SMR | C7: SMR compensates for solar/wind intermittency | D7: 80 | E7: 75 | F7: 85
A8: Combined Stress | B8: Solar + Nuclear | C8: Highest reliability, security, and water support under worst-case stress | D8: 92 | E8: 89 | F8: 95
A10: Confidence for the Combined Stress recommendation: 89% (based on scenario score margin over next-best strategy).

Sheet Methodology
A1: Methodology — AI Decision Engine Logic
A2: Collect Saudi Energy Data | B2: Description
A3: Validate Data | B3: Data Collection: gather nuclear plant, renewable (solar/wind/battery), demand, weather, water availability, and market price data (Saudi_Data, Weather_Data, Water_Resources, Market_Data sheets)
A4: Forecast Demand | B4: Data Processing: receive, validate, clean, and normalize incoming data before storage
A5: Run Scenarios | B5: AI Forecasting: project electricity demand, solar/wind output, prices, and water availability (AI_Forecast sheet)
A6: Calculate Decision Score | B6: AI Decision Engine: analyze demand, nuclear/solar/wind/battery capacity, operating cost, water consumption, carbon emissions, and grid stability (Decision_Engine sheet)
A7: Generate Recommendation | B7: Scenario Evaluation: test candidate mixes — Nuclear+Solar, Nuclear+Solar+Wind, Nuclear+Battery, Nuclear+Solar+Wind+Battery — under stress scenarios (Scenario_Simulator sheet)
A8: Dashboard | B8: Multi-Criteria Optimization: weight cost, reliability, water, emissions, and renewable utilization to compute a Decision Score
A9: 7 | B9: AI Recommendation: output the recommended energy mix with expected cost, water, emissions, and reliability (AI_Recommendation, Results sheets)
A10: 8 | B10: Dashboard: present live energy mix, KPIs, alerts, and forecasts for decision-makers (Dashboard, KPI_Dashboard sheets)
